pydigikey/__init__.py
pydigikey/client.py
pydigikey/models.py
pydigikey/py.typed
pydigikey-0.3.4.dist-info/licenses/LICENSE
pydigikey-0.3.4.dist-info/WHEEL
pydigikey-0.3.4.dist-info/METADATA
pydigikey-0.3.4.dist-info/RECORD
