Metadata-Version: 2.4
Name: pydigikey
Version: 0.3.4
Summary: Digikey API
Author: ferris
Author-email: ferris <ferris@devdroplets.com>
License-Expression: GPL-3.0-or-later
License-File: LICENSE
Requires-Dist: httpx>=0.24.0
Requires-Dist: pydantic>=2.0.0
Requires-Dist: sniffio
Requires-Dist: trio
Requires-Python: >=3.10
Project-URL: Homepage, https://codeberg.org/ferrisk/pydigikey
Project-URL: Issues, https://codeberg.org/ferrisk/pydigikey/issues
Project-URL: Repository, https://codeberg.org/ferrisk/pydigikey.git
